[
  {
    "url": "https://cpanel02wh.bkk1.cloud.z.com/~cp343601//appmain/Assistenza/",
    "cert_valid_days": 89,
    "cert_days_to_expire": 57,
    "cert_issuer_len": 18,
    "cert_subject_cn_mismatch": 0,
    "status_code": 404,
    "resp_time_ms": 406,
    "redirect_count": 0,
    "final_url_mismatch": 0,
    "content_length": 10154,
    "mime_type": "text/html",
    "form_count": 0,
    "password_input_count": 0,
    "suspicious_js_calls": 0,
    "base64_count": 1,
    "external_link_count": 2,
    "external_resource_count": 0
  },
  {
    "url": "https://ghsdsdfsdjsdfdhsdfsdfsdfsdtrwefsdfgsdrwsfsdfsdfsdviocemessaged.weeblysite.com/",
    "cert_valid_days": 90,
    "cert_days_to_expire": 47,
    "cert_issuer_len": 26,
    "cert_subject_cn_mismatch": 1,
    "status_code": 404,
    "resp_time_ms": 703,
    "redirect_count": 0,
    "final_url_mismatch": 0,
    "content_length": 1547,
    "mime_type": "text/html",
    "form_count": 0,
    "password_input_count": 0,
    "suspicious_js_calls": 0,
    "base64_count": 0,
    "external_link_count": 0,
    "external_resource_count": 0
  },
  {
    "url": "https://s.free.fr/aySJHA2u",
    "cert_valid_days": 390,
    "cert_days_to_expire": 43,
    "cert_issuer_len": 52,
    "cert_subject_cn_mismatch": 1,
    "status_code": 404,
    "resp_time_ms": 1234,
    "redirect_count": 0,
    "final_url_mismatch": 0,
    "content_length": 40,
    "mime_type": "application/json",
    "form_count": 0,
    "password_input_count": 0,
    "suspicious_js_calls": 0,
    "base64_count": 0,
    "external_link_count": 0,
    "external_resource_count": 0
  },
  {
    "url": "https://www.google.com/?onboarding_creation_ts=1702982665611&amp;source_caller=ui&amp;shortlink=u95g39zq&amp;pid=my_media_source&amp;id=8&amp;url=https://cs.money/prime/&amp;gclid=EAIaIQobChMIvJOW4NGdgwMVo5NoCR30qAFkEAAYASAAEgIGqPD_BwE",
    "cert_valid_days": 83,
    "cert_days_to_expire": 63,
    "cert_issuer_len": 26,
    "cert_subject_cn_mismatch": 0,
    "status_code": 200,
    "resp_time_ms": 302,
    "redirect_count": 0,
    "final_url_mismatch": 0,
    "content_length": 18422,
    "mime_type": "text/html",
    "form_count": 1,
    "password_input_count": 0,
    "suspicious_js_calls": 4,
    "base64_count": 0,
    "external_link_count": 5,
    "external_resource_count": 0
  },
  {
    "url": "https://unitednewsservice.com/?onboarding_creation_ts=1701958366716&amp;source_caller=ui&amp;shortlink=b22d9cyo&amp;pid=my_media_source&amp;id=8&amp;url=https://buff.163.com/goods/756319&amp;gclid=EAIaIQobChMIyv-59c6dgwMVe5poCR3CxwKhEAAYASAAEgIfxfD_BwE",
    "cert_valid_days": 89,
    "cert_days_to_expire": 67,
    "cert_issuer_len": 18,
    "cert_subject_cn_mismatch": 1,
    "status_code": 200,
    "resp_time_ms": 605,
    "redirect_count": 0,
    "final_url_mismatch": 0,
    "content_length": 1735,
    "mime_type": "text/html",
    "form_count": 0,
    "password_input_count": 0,
    "suspicious_js_calls": 1,
    "base64_count": 0,
    "external_link_count": 0,
    "external_resource_count": 0
  },
  {
    "url": "https://ioqwueiwqheiwqbudsadsa.onelink.me/w3i3/b22d9cyo/?url=https://buff.163.com/goods/756319&amp;id=8&amp;af_android_url=https://buff.163.com/goods/756319&amp;af_ios_url=https://buff.163.com/goods/756319&amp;af_web_dp=https://buff.163.com/goods/756319&amp;gclid=EAIaIQobChMIyv-59c6dgwMVe5poCR3CxwKhEAAYASAAEgIfxfD_BwE",
    "cert_valid_days": 394,
    "cert_days_to_expire": 335,
    "cert_issuer_len": 27,
    "cert_subject_cn_mismatch": 1,
    "status_code": 200,
    "resp_time_ms": 1103,
    "redirect_count": 0,
    "final_url_mismatch": 0,
    "content_length": 2089,
    "mime_type": "text/html",
    "form_count": 0,
    "password_input_count": 0,
    "suspicious_js_calls": 0,
    "base64_count": 0,
    "external_link_count": 0,
    "external_resource_count": 3
  },
  {
    "url": "https://digjrighjuhd.onelink.me/MauH/3hn20udr/?url=https://buff.market/&amp;id=8&amp;af_android_url=https://buff.market/&amp;af_ios_url=https://buff.market/&amp;af_web_dp=https://buff.market/&amp;gclid=EAIaIQobChMI3tbAyc-dgwMVBAIGAB1OlwVfEAAYASAAEgJGffD_BwE",
    "cert_valid_days": 394,
    "cert_days_to_expire": 335,
    "cert_issuer_len": 27,
    "cert_subject_cn_mismatch": 1,
    "status_code": 200,
    "resp_time_ms": 1105,
    "redirect_count": 0,
    "final_url_mismatch": 0,
    "content_length": 2089,
    "mime_type": "text/html",
    "form_count": 0,
    "password_input_count": 0,
    "suspicious_js_calls": 0,
    "base64_count": 0,
    "external_link_count": 0,
    "external_resource_count": 3
  },
  {
    "url": "https://solzys-sity.webflow.io/",
    "cert_valid_days": 90,
    "cert_days_to_expire": 35,
    "cert_issuer_len": 26,
    "cert_subject_cn_mismatch": 1,
    "status_code": 404,
    "resp_time_ms": 97,
    "redirect_count": 0,
    "final_url_mismatch": 0,
    "content_length": 906,
    "mime_type": "text/html",
    "form_count": 0,
    "password_input_count": 0,
    "suspicious_js_calls": 0,
    "base64_count": 0,
    "external_link_count": 0,
    "external_resource_count": 1
  },
  {
    "url": "https://pub-29132efbdf684e8f818bbd467c48feec.r2.dev/cp148q-0iPx.html#<a href=\"/cdn-cgi/l/email-protection\" class=\"__cf_email__\" data-cfemail=\"6410011710240703004a1410\">[email?†protected]</a>",
    "cert_valid_days": 89,
    "cert_days_to_expire": 80,
    "cert_issuer_len": 17,
    "cert_subject_cn_mismatch": 1,
    "status_code": 401,
    "resp_time_ms": 70,
    "redirect_count": 0,
    "final_url_mismatch": 0,
    "content_length": 16794,
    "mime_type": "text/html",
    "form_count": 0,
    "password_input_count": 0,
    "suspicious_js_calls": 0,
    "base64_count": 0,
    "external_link_count": 1,
    "external_resource_count": 1
  },
  {
    "url": "https://3kelincisport.com/?onboarding_creation_ts=1701701828348&amp;source_caller=ui&amp;shortlink=hevtt9vb&amp;pid=my_media_source&amp;id=8&amp;url=https://dmarket.com/blog/best-csgo-players-2021/&amp;gclid=EAIaIQobChMI_7XvoMydgwMVIqKDBx0igwkNEAAYASAAEgJLc_D_BwE",
    "cert_valid_days": 89,
    "cert_days_to_expire": 66,
    "cert_issuer_len": 18,
    "cert_subject_cn_mismatch": 0,
    "status_code": 200,
    "resp_time_ms": 597,
    "redirect_count": 0,
    "final_url_mismatch": 0,
    "content_length": 1764,
    "mime_type": "text/html",
    "form_count": 0,
    "password_input_count": 0,
    "suspicious_js_calls": 1,
    "base64_count": 0,
    "external_link_count": 0,
    "external_resource_count": 0
  },
  {
    "url": "https://dedmampap.onelink.me/PLpx/hevtt9vb/?url=https://dmarket.com/blog/best-csgo-players-2021/&amp;id=8&amp;af_android_url=https://dmarket.com/blog/best-csgo-players-2021/&amp;af_ios_url=https://dmarket.com/blog/best-csgo-players-2021/&amp;af_web_dp=https://dmarket.com/blog/best-csgo-players-2021/&amp;gclid=EAIaIQobChMI_7XvoMydgwMVIqKDBx0igwkNEAAYASAAEgJLc_D_BwE",
    "cert_valid_days": 394,
    "cert_days_to_expire": 335,
    "cert_issuer_len": 27,
    "cert_subject_cn_mismatch": 1,
    "status_code": 200,
    "resp_time_ms": 1120,
    "redirect_count": 0,
    "final_url_mismatch": 0,
    "content_length": 2089,
    "mime_type": "text/html",
    "form_count": 0,
    "password_input_count": 0,
    "suspicious_js_calls": 0,
    "base64_count": 0,
    "external_link_count": 0,
    "external_resource_count": 3
  },
  {
    "url": "https://trackinpagesads.onelink.me/x7kL/val14flo/?url=https://cs.money/privacy&amp;id=19&amp;af_android_url=https://cs.money/privacy&amp;af_ios_url=https://cs.money/privacy&amp;af_web_dp=https://cs.money/privacy&amp;gclid=EAIaIQobChMIs_3ars2dgwMVv4toCR0a-AiBEAAYASAAEgJ1xPD_BwE",
    "cert_valid_days": 394,
    "cert_days_to_expire": 335,
    "cert_issuer_len": 27,
    "cert_subject_cn_mismatch": 1,
    "status_code": 200,
    "resp_time_ms": 1898,
    "redirect_count": 1,
    "final_url_mismatch": 1,
    "content_length": 1516,
    "mime_type": "text/html",
    "form_count": 0,
    "password_input_count": 0,
    "suspicious_js_calls": 1,
    "base64_count": 0,
    "external_link_count": 1,
    "external_resource_count": 0
  },
  {
    "url": "https://dfdfdsddsdsdfxfxfxf.weebly.com/",
    "cert_valid_days": 89,
    "cert_days_to_expire": 50,
    "cert_issuer_len": 17,
    "cert_subject_cn_mismatch": 1,
    "status_code": 404,
    "resp_time_ms": 336,
    "redirect_count": 0,
    "final_url_mismatch": 0,
    "content_length": 3909,
    "mime_type": "text/html",
    "form_count": 0,
    "password_input_count": 0,
    "suspicious_js_calls": 0,
    "base64_count": 0,
    "external_link_count": 0,
    "external_resource_count": 1
  },
  {
    "url": "https://gyemini09logen.mystrikingly.com/",
    "cert_valid_days": 394,
    "cert_days_to_expire": 340,
    "cert_issuer_len": 27,
    "cert_subject_cn_mismatch": 1,
    "status_code": 403,
    "resp_time_ms": 49,
    "redirect_count": 0,
    "final_url_mismatch": 0,
    "content_length": 919,
    "mime_type": "text/html",
    "form_count": 0,
    "password_input_count": 0,
    "suspicious_js_calls": 0,
    "base64_count": 0,
    "external_link_count": 0,
    "external_resource_count": 0
  },
  {
    "url": "https://docs.google.com/presentation/d/e/2PACX-1vQLAL6AMRhXd3i-7cEh_r9PhhmQbHcLAf6Iwtl7lZh2h9c4A21KwEvjph2ElJx6JyhsFv7RsK1evGx-/pub?start=false&amp;loop=false&amp;delayms=3000",
    "cert_valid_days": 83,
    "cert_days_to_expire": 63,
    "cert_issuer_len": 26,
    "cert_subject_cn_mismatch": 1,
    "status_code": 200,
    "resp_time_ms": 563,
    "redirect_count": 0,
    "final_url_mismatch": 0,
    "content_length": 77170,
    "mime_type": "text/html",
    "form_count": 0,
    "password_input_count": 0,
    "suspicious_js_calls": 0,
    "base64_count": 0,
    "external_link_count": 0,
    "external_resource_count": 3
  },
  {
    "url": "https://supporthelp6666.pages.net.br/a",
    "cert_valid_days": 89,
    "cert_days_to_expire": 86,
    "cert_issuer_len": 17,
    "cert_subject_cn_mismatch": 1,
    "status_code": 403,
    "resp_time_ms": 312,
    "redirect_count": 0,
    "final_url_mismatch": 0,
    "content_length": 291,
    "mime_type": "text/html",
    "form_count": 0,
    "password_input_count": 0,
    "suspicious_js_calls": 0,
    "base64_count": 0,
    "external_link_count": 2,
    "external_resource_count": 0
  },
  {
    "url": "https://9999999999.pages.net.br/aw",
    "cert_valid_days": 89,
    "cert_days_to_expire": 86,
    "cert_issuer_len": 17,
    "cert_subject_cn_mismatch": 1,
    "status_code": 404,
    "resp_time_ms": 1371,
    "redirect_count": 0,
    "final_url_mismatch": 0,
    "content_length": 24357,
    "mime_type": "text/html",
    "form_count": 0,
    "password_input_count": 0,
    "suspicious_js_calls": 0,
    "base64_count": 1,
    "external_link_count": 0,
    "external_resource_count": 3
  },
  {
    "url": "http://axieinfinity.kesug.com",
    "cert_valid_days": 0,
    "cert_days_to_expire": 0,
    "cert_issuer_len": 0,
    "cert_subject_cn_mismatch": 1,
    "status_code": 200,
    "resp_time_ms": 662,
    "redirect_count": 0,
    "final_url_mismatch": 0,
    "content_length": 1066,
    "mime_type": "text/html",
    "form_count": 0,
    "password_input_count": 0,
    "suspicious_js_calls": 0,
    "base64_count": 1,
    "external_link_count": 0,
    "external_resource_count": 1
  },
  {
    "url": "https://cl.s13.exct.net/?qs=dac93f3ccbcdd8e09c9c8a27fc5efe52fde70ec1717e026fa631a21b1b9d5b2bdd620a848a4cf01139a643bacd999740",
    "cert_valid_days": 396,
    "cert_days_to_expire": 75,
    "cert_issuer_len": 56,
    "cert_subject_cn_mismatch": 0,
    "status_code": 200,
    "resp_time_ms": 2250,
    "redirect_count": 1,
    "final_url_mismatch": 0,
    "content_length": 269,
    "mime_type": "text/html",
    "form_count": 0,
    "password_input_count": 0,
    "suspicious_js_calls": 0,
    "base64_count": 0,
    "external_link_count": 0,
    "external_resource_count": 0
  },
  {
    "url": "https://menahanngising.binasol.com/dashboard",
    "cert_valid_days": 365,
    "cert_days_to_expire": 151,
    "cert_issuer_len": 66,
    "cert_subject_cn_mismatch": 0,
    "status_code": 436,
    "resp_time_ms": 1216,
    "redirect_count": 0,
    "final_url_mismatch": 0,
    "content_length": 0,
    "mime_type": "",
    "form_count": 0,
    "password_input_count": 0,
    "suspicious_js_calls": 0,
    "base64_count": 0,
    "external_link_count": 0,
    "external_resource_count": 0
  },
  {
    "url": "https://yahoo-103267-102127.weeblysite.com/",
    "cert_valid_days": 90,
    "cert_days_to_expire": 47,
    "cert_issuer_len": 26,
    "cert_subject_cn_mismatch": 1,
    "status_code": 404,
    "resp_time_ms": 753,
    "redirect_count": 0,
    "final_url_mismatch": 0,
    "content_length": 1547,
    "mime_type": "text/html",
    "form_count": 0,
    "password_input_count": 0,
    "suspicious_js_calls": 0,
    "base64_count": 0,
    "external_link_count": 0,
    "external_resource_count": 0
  },
  {
    "url": "https://metamask-uswallet.webflow.io/",
    "cert_valid_days": 90,
    "cert_days_to_expire": 35,
    "cert_issuer_len": 26,
    "cert_subject_cn_mismatch": 1,
    "status_code": 404,
    "resp_time_ms": 760,
    "redirect_count": 0,
    "final_url_mismatch": 0,
    "content_length": 906,
    "mime_type": "text/html",
    "form_count": 0,
    "password_input_count": 0,
    "suspicious_js_calls": 0,
    "base64_count": 0,
    "external_link_count": 0,
    "external_resource_count": 1
  },
  {
    "url": "https://new.express.adobe.com/webpage/l4JVIhwqRbPZN",
    "cert_valid_days": 394,
    "cert_days_to_expire": 338,
    "cert_issuer_len": 27,
    "cert_subject_cn_mismatch": 1,
    "status_code": 200,
    "resp_time_ms": 771,
    "redirect_count": 0,
    "final_url_mismatch": 0,
    "content_length": 72654,
    "mime_type": "text/html",
    "form_count": 0,
    "password_input_count": 0,
    "suspicious_js_calls": 0,
    "base64_count": 1,
    "external_link_count": 0,
    "external_resource_count": 0
  },
  {
    "url": "https://uphold-lgin.jimdofree.com/",
    "cert_valid_days": 90,
    "cert_days_to_expire": 58,
    "cert_issuer_len": 26,
    "cert_subject_cn_mismatch": 1,
    "status_code": 404,
    "resp_time_ms": 887,
    "redirect_count": 0,
    "final_url_mismatch": 0,
    "content_length": 0,
    "mime_type": "text/html",
    "form_count": 0,
    "password_input_count": 0,
    "suspicious_js_calls": 0,
    "base64_count": 0,
    "external_link_count": 0,
    "external_resource_count": 0
  },
  {
    "url": "https://docs.google.com/presentation/d/e/2PACX-1vRPEvlQLoiqh2aPi6_1fWLnd-_Ihq4VWTA2EX86kY0o0b5VQBXdcTXuONWP9quf_RRtDM4ymH3fnFyR/pub?start=false&amp;loop=false&amp;delayms=3000",
    "cert_valid_days": 83,
    "cert_days_to_expire": 63,
    "cert_issuer_len": 26,
    "cert_subject_cn_mismatch": 1,
    "status_code": 200,
    "resp_time_ms": 756,
    "redirect_count": 0,
    "final_url_mismatch": 0,
    "content_length": 83826,
    "mime_type": "text/html",
    "form_count": 0,
    "password_input_count": 0,
    "suspicious_js_calls": 0,
    "base64_count": 0,
    "external_link_count": 0,
    "external_resource_count": 3
  },
  {
    "url": "https://keepo.io/loginmyattaccountnow/",
    "cert_valid_days": 393,
    "cert_days_to_expire": 186,
    "cert_issuer_len": 27,
    "cert_subject_cn_mismatch": 0,
    "status_code": 404,
    "resp_time_ms": 1913,
    "redirect_count": 0,
    "final_url_mismatch": 0,
    "content_length": 15084,
    "mime_type": "text/html",
    "form_count": 0,
    "password_input_count": 0,
    "suspicious_js_calls": 0,
    "base64_count": 0,
    "external_link_count": 0,
    "external_resource_count": 1
  },
  {
    "url": "https://new.express.adobe.com/webpage/QZXjEbMqcfUi2",
    "cert_valid_days": 394,
    "cert_days_to_expire": 338,
    "cert_issuer_len": 27,
    "cert_subject_cn_mismatch": 1,
    "status_code": 200,
    "resp_time_ms": 879,
    "redirect_count": 0,
    "final_url_mismatch": 0,
    "content_length": 72654,
    "mime_type": "text/html",
    "form_count": 0,
    "password_input_count": 0,
    "suspicious_js_calls": 0,
    "base64_count": 1,
    "external_link_count": 0,
    "external_resource_count": 0
  },
  {
    "url": "https://docs.google.com/presentation/d/e/2PACX-1vTFMgBlgu8yhVyeaPFqO_vaCcb_u3gqU-IYBmlnt1owQjJIIbT7dYizdy6ZB5qCks9c3yTEoJRUxLL2/pub?start=false&amp;loop=false&amp;delayms=3000",
    "cert_valid_days": 83,
    "cert_days_to_expire": 63,
    "cert_issuer_len": 26,
    "cert_subject_cn_mismatch": 1,
    "status_code": 200,
    "resp_time_ms": 656,
    "redirect_count": 0,
    "final_url_mismatch": 0,
    "content_length": 82006,
    "mime_type": "text/html",
    "form_count": 0,
    "password_input_count": 0,
    "suspicious_js_calls": 0,
    "base64_count": 0,
    "external_link_count": 0,
    "external_resource_count": 3
  },
  {
    "url": "https://new.express.adobe.com/webpage/On9SrByPHD1QZ",
    "cert_valid_days": 394,
    "cert_days_to_expire": 338,
    "cert_issuer_len": 27,
    "cert_subject_cn_mismatch": 1,
    "status_code": 200,
    "resp_time_ms": 744,
    "redirect_count": 0,
    "final_url_mismatch": 0,
    "content_length": 72654,
    "mime_type": "text/html",
    "form_count": 0,
    "password_input_count": 0,
    "suspicious_js_calls": 0,
    "base64_count": 1,
    "external_link_count": 0,
    "external_resource_count": 0
  },
  {
    "url": "https://docs.google.com/presentation/d/e/2PACX-1vRw6BHL0kL9eSvJZI76dxajpjwbiVimyrW4aKY_iz4dDNIJXYCGNmwg8NvOnn6z6u5hc-XgEiE5OdGu/pub?start=false&amp;loop=false&amp;delayms=3000",
    "cert_valid_days": 83,
    "cert_days_to_expire": 63,
    "cert_issuer_len": 26,
    "cert_subject_cn_mismatch": 1,
    "status_code": 200,
    "resp_time_ms": 726,
    "redirect_count": 0,
    "final_url_mismatch": 0,
    "content_length": 82507,
    "mime_type": "text/html",
    "form_count": 0,
    "password_input_count": 0,
    "suspicious_js_calls": 0,
    "base64_count": 0,
    "external_link_count": 0,
    "external_resource_count": 3
  },
  {
    "url": "https://docs.google.com/presentation/d/e/2PACX-1vRURBCnTnYRAAsUGE2Lw-RRDGR0uAt7FjNNKHhtlv3VpSlby79j2RWfOuzk-8k8bfzCbYQkan_erEbJ/pub?start=false&amp;loop=false&amp;delayms=3000",
    "cert_valid_days": 83,
    "cert_days_to_expire": 63,
    "cert_issuer_len": 26,
    "cert_subject_cn_mismatch": 1,
    "status_code": 410,
    "resp_time_ms": 735,
    "redirect_count": 0,
    "final_url_mismatch": 0,
    "content_length": 3286,
    "mime_type": "text/html",
    "form_count": 0,
    "password_input_count": 0,
    "suspicious_js_calls": 0,
    "base64_count": 0,
    "external_link_count": 0,
    "external_resource_count": 2
  },
  {
    "url": "https://docs.google.com/presentation/d/e/2PACX-1vTkLjLxtOv05YOGEjFpp7FE-WjcwRIx4lq9x_nfzG8Oq9X64e0UcJO0uwateus49mCle8YQjUa8dh8l/pub?start=false&amp;loop=false&amp;delayms=3000&amp;slide=id.p",
    "cert_valid_days": 83,
    "cert_days_to_expire": 63,
    "cert_issuer_len": 26,
    "cert_subject_cn_mismatch": 1,
    "status_code": 200,
    "resp_time_ms": 756,
    "redirect_count": 0,
    "final_url_mismatch": 0,
    "content_length": 79455,
    "mime_type": "text/html",
    "form_count": 0,
    "password_input_count": 0,
    "suspicious_js_calls": 0,
    "base64_count": 0,
    "external_link_count": 0,
    "external_resource_count": 3
  },
  {
    "url": "https://dfhrewtrt.w3spaces.com/saved-from-Tryit-2023-12-18html",
    "cert_valid_days": 394,
    "cert_days_to_expire": 341,
    "cert_issuer_len": 27,
    "cert_subject_cn_mismatch": 1,
    "status_code": 200,
    "resp_time_ms": 1961,
    "redirect_count": 0,
    "final_url_mismatch": 0,
    "content_length": 12984,
    "mime_type": "text/html",
    "form_count": 0,
    "password_input_count": 0,
    "suspicious_js_calls": 0,
    "base64_count": 0,
    "external_link_count": 4,
    "external_resource_count": 1
  },
  {
    "url": "https://docs.google.com/presentation/d/e/2PACX-1vR6iy1aC5Kma1ZcKFwoLtGgLfCgAIRseq-sWTvO_-xDpuH_uRdJnes5vKpk-R-ATJe9n5mKTxkY83ZE/pub?start=false&amp;loop=true&amp;delayms=3000",
    "cert_valid_days": 83,
    "cert_days_to_expire": 63,
    "cert_issuer_len": 26,
    "cert_subject_cn_mismatch": 1,
    "status_code": 410,
    "resp_time_ms": 596,
    "redirect_count": 0,
    "final_url_mismatch": 0,
    "content_length": 3286,
    "mime_type": "text/html",
    "form_count": 0,
    "password_input_count": 0,
    "suspicious_js_calls": 0,
    "base64_count": 0,
    "external_link_count": 0,
    "external_resource_count": 2
  },
  {
    "url": "https://ytaaes.weeblysite.com/",
    "cert_valid_days": 90,
    "cert_days_to_expire": 47,
    "cert_issuer_len": 26,
    "cert_subject_cn_mismatch": 1,
    "status_code": 404,
    "resp_time_ms": 666,
    "redirect_count": 0,
    "final_url_mismatch": 0,
    "content_length": 1547,
    "mime_type": "text/html",
    "form_count": 0,
    "password_input_count": 0,
    "suspicious_js_calls": 0,
    "base64_count": 0,
    "external_link_count": 0,
    "external_resource_count": 0
  },
  {
    "url": "https://upholdylogg.mystrikingly.com/",
    "cert_valid_days": 394,
    "cert_days_to_expire": 340,
    "cert_issuer_len": 27,
    "cert_subject_cn_mismatch": 1,
    "status_code": 403,
    "resp_time_ms": 64,
    "redirect_count": 0,
    "final_url_mismatch": 0,
    "content_length": 919,
    "mime_type": "text/html",
    "form_count": 0,
    "password_input_count": 0,
    "suspicious_js_calls": 0,
    "base64_count": 0,
    "external_link_count": 0,
    "external_resource_count": 0
  },
  {
    "url": "https://taplink.cc/iuyg",
    "cert_valid_days": 89,
    "cert_days_to_expire": 54,
    "cert_issuer_len": 17,
    "cert_subject_cn_mismatch": 0,
    "status_code": 404,
    "resp_time_ms": 1542,
    "redirect_count": 0,
    "final_url_mismatch": 0,
    "content_length": 1637,
    "mime_type": "text/html",
    "form_count": 0,
    "password_input_count": 0,
    "suspicious_js_calls": 0,
    "base64_count": 0,
    "external_link_count": 0,
    "external_resource_count": 1
  },
  {
    "url": "https://docs.google.com/presentation/d/e/2PACX-1vRQvb6KePnetnbzClvnxDNm73qUJU8hHtKbj9IILaAQHSEWQjEW5zOu4FJXBSs3SZltjRNAsjGIPja7/pub?start=false&amp;loop=false&amp;delayms=3000",
    "cert_valid_days": 83,
    "cert_days_to_expire": 63,
    "cert_issuer_len": 26,
    "cert_subject_cn_mismatch": 1,
    "status_code": 200,
    "resp_time_ms": 759,
    "redirect_count": 0,
    "final_url_mismatch": 0,
    "content_length": 81668,
    "mime_type": "text/html",
    "form_count": 0,
    "password_input_count": 0,
    "suspicious_js_calls": 0,
    "base64_count": 0,
    "external_link_count": 0,
    "external_resource_count": 3
  },
  {
    "url": "https://docs.google.com/presentation/d/e/2PACX-1vRjymIMs3_gnZEseVLi9zFPJl-19l4haYR_uTy-19OJ37RPf_N1rObQ9bFnjL5HpcMusnUzc15Qi2rd/pub?start=false&amp;loop=false&amp;delayms=3000",
    "cert_valid_days": 83,
    "cert_days_to_expire": 63,
    "cert_issuer_len": 26,
    "cert_subject_cn_mismatch": 1,
    "status_code": 200,
    "resp_time_ms": 638,
    "redirect_count": 0,
    "final_url_mismatch": 0,
    "content_length": 73670,
    "mime_type": "text/html",
    "form_count": 0,
    "password_input_count": 0,
    "suspicious_js_calls": 0,
    "base64_count": 0,
    "external_link_count": 0,
    "external_resource_count": 3
  },
  {
    "url": "http://notificardlinea.webcindario.com",
    "cert_valid_days": 89,
    "cert_days_to_expire": 13,
    "cert_issuer_len": 18,
    "cert_subject_cn_mismatch": 1,
    "status_code": 200,
    "resp_time_ms": 611,
    "redirect_count": 0,
    "final_url_mismatch": 0,
    "content_length": 2624,
    "mime_type": "text/html",
    "form_count": 0,
    "password_input_count": 0,
    "suspicious_js_calls": 0,
    "base64_count": 0,
    "external_link_count": 1,
    "external_resource_count": 0
  },
  {
    "url": "https://caldodepiedra.com.mx/css/",
    "cert_valid_days": 89,
    "cert_days_to_expire": 78,
    "cert_issuer_len": 18,
    "cert_subject_cn_mismatch": 1,
    "status_code": 403,
    "resp_time_ms": 910,
    "redirect_count": 0,
    "final_url_mismatch": 0,
    "content_length": 318,
    "mime_type": "text/html",
    "form_count": 0,
    "password_input_count": 0,
    "suspicious_js_calls": 0,
    "base64_count": 0,
    "external_link_count": 0,
    "external_resource_count": 0
  },
  {
    "url": "https://docs.google.com/presentation/d/e/2PACX-1vT52UPn2hq9GYiWAMTi8ZR-Q5lUmqc6dIlqvRhTQFkUKH6ZF0JF78ECUDd_hpO7o87qVnFB7QmM6e5o/pub?start=false&amp;loop=false&amp;delayms=3000&amp;slide=id.p",
    "cert_valid_days": 83,
    "cert_days_to_expire": 63,
    "cert_issuer_len": 26,
    "cert_subject_cn_mismatch": 1,
    "status_code": 200,
    "resp_time_ms": 841,
    "redirect_count": 0,
    "final_url_mismatch": 0,
    "content_length": 93079,
    "mime_type": "text/html",
    "form_count": 0,
    "password_input_count": 0,
    "suspicious_js_calls": 0,
    "base64_count": 0,
    "external_link_count": 0,
    "external_resource_count": 3
  },
  {
    "url": "https://new.express.adobe.com/webpage/uxeU9Z2WinG63",
    "cert_valid_days": 394,
    "cert_days_to_expire": 338,
    "cert_issuer_len": 27,
    "cert_subject_cn_mismatch": 1,
    "status_code": 200,
    "resp_time_ms": 813,
    "redirect_count": 0,
    "final_url_mismatch": 0,
    "content_length": 72654,
    "mime_type": "text/html",
    "form_count": 0,
    "password_input_count": 0,
    "suspicious_js_calls": 0,
    "base64_count": 1,
    "external_link_count": 0,
    "external_resource_count": 0
  },
  {
    "url": "https://www.cakeresume.com/verifedbtconnectphp",
    "cert_valid_days": 90,
    "cert_days_to_expire": 85,
    "cert_issuer_len": 26,
    "cert_subject_cn_mismatch": 1,
    "status_code": 404,
    "resp_time_ms": 1355,
    "redirect_count": 1,
    "final_url_mismatch": 1,
    "content_length": 170942,
    "mime_type": "text/html",
    "form_count": 0,
    "password_input_count": 0,
    "suspicious_js_calls": 0,
    "base64_count": 0,
    "external_link_count": 19,
    "external_resource_count": 3
  },
  {
    "url": "https://docs.google.com/presentation/d/e/2PACX-1vSPSIMYdrzMkjjeNWfPJXEL6N2eJnF-bRte8VQDYJIm0SW_N5nBVwuRv3Kh6ABLxTcMPt2zRnylRVcZ/pub?start=false&amp;loop=false&amp;delayms=3000&amp;slide=id.p",
    "cert_valid_days": 83,
    "cert_days_to_expire": 63,
    "cert_issuer_len": 26,
    "cert_subject_cn_mismatch": 1,
    "status_code": 403,
    "resp_time_ms": 528,
    "redirect_count": 0,
    "final_url_mismatch": 0,
    "content_length": 2994,
    "mime_type": "text/html",
    "form_count": 0,
    "password_input_count": 0,
    "suspicious_js_calls": 0,
    "base64_count": 0,
    "external_link_count": 0,
    "external_resource_count": 2
  },
  {
    "url": "https://docs.google.com/presentation/d/e/2PACX-1vT4WkOKAqFirtKIQh9kvMSva8Y_xMyo7E1s-M8skdW5SweA8ZtLFhzdakfoV9mvSjbtBGCoqdzLbAny/pub?start=false&amp;loop=false&amp;delayms=3000",
    "cert_valid_days": 83,
    "cert_days_to_expire": 63,
    "cert_issuer_len": 26,
    "cert_subject_cn_mismatch": 1,
    "status_code": 403,
    "resp_time_ms": 567,
    "redirect_count": 0,
    "final_url_mismatch": 0,
    "content_length": 2994,
    "mime_type": "text/html",
    "form_count": 0,
    "password_input_count": 0,
    "suspicious_js_calls": 0,
    "base64_count": 0,
    "external_link_count": 0,
    "external_resource_count": 2
  },
  {
    "url": "https://docs.google.com/presentation/d/e/2PACX-1vQzmuPrH1NA9gtrelcbeU3iDjSgEAaeC69Jd0ykJyTyB4YuDl4IxQY_0Q-uVAGCceMBaBxIGaZuw9VV/pub?start=false&amp;loop=false&amp;delayms=3000&amp;slide=id.p",
    "cert_valid_days": 83,
    "cert_days_to_expire": 63,
    "cert_issuer_len": 26,
    "cert_subject_cn_mismatch": 1,
    "status_code": 410,
    "resp_time_ms": 564,
    "redirect_count": 0,
    "final_url_mismatch": 0,
    "content_length": 3286,
    "mime_type": "text/html",
    "form_count": 0,
    "password_input_count": 0,
    "suspicious_js_calls": 0,
    "base64_count": 0,
    "external_link_count": 0,
    "external_resource_count": 2
  },
  {
    "url": "https://new.express.adobe.com/webpage/w26YbODZV7cf3",
    "cert_valid_days": 394,
    "cert_days_to_expire": 338,
    "cert_issuer_len": 27,
    "cert_subject_cn_mismatch": 1,
    "status_code": 200,
    "resp_time_ms": 643,
    "redirect_count": 0,
    "final_url_mismatch": 0,
    "content_length": 72654,
    "mime_type": "text/html",
    "form_count": 0,
    "password_input_count": 0,
    "suspicious_js_calls": 0,
    "base64_count": 1,
    "external_link_count": 0,
    "external_resource_count": 0
  },
  {
    "url": "https://pub-b591593e6a474e90b862c81507d5d12a.r2.dev/linking.html#<a href=\"/cdn-cgi/l/email-protection\" class=\"__cf_email__\" data-cfemail=\"7d053d05531e1210\">[email?†protected]</a>",
    "cert_valid_days": 89,
    "cert_days_to_expire": 80,
    "cert_issuer_len": 17,
    "cert_subject_cn_mismatch": 1,
    "status_code": 401,
    "resp_time_ms": 105,
    "redirect_count": 0,
    "final_url_mismatch": 0,
    "content_length": 16794,
    "mime_type": "text/html",
    "form_count": 0,
    "password_input_count": 0,
    "suspicious_js_calls": 0,
    "base64_count": 0,
    "external_link_count": 1,
    "external_resource_count": 1
  },
  {
    "url": "https://pub-8f0c7a409fba4da9b5e820fe9817ee46.r2.dev/OWa-app-outlook-ken.html#<a href=\"/cdn-cgi/l/email-protection\" class=\"__cf_email__\" data-cfemail=\"423a023a6c212d2f\">[email?†protected]</a>",
    "cert_valid_days": 89,
    "cert_days_to_expire": 80,
    "cert_issuer_len": 17,
    "cert_subject_cn_mismatch": 1,
    "status_code": 403,
    "resp_time_ms": 86,
    "redirect_count": 0,
    "final_url_mismatch": 0,
    "content_length": 4096,
    "mime_type": "text/html",
    "form_count": 0,
    "password_input_count": 0,
    "suspicious_js_calls": 0,
    "base64_count": 0,
    "external_link_count": 2,
    "external_resource_count": 0
  },
  {
    "url": "https://americuer.com/",
    "cert_valid_days": 89,
    "cert_days_to_expire": 41,
    "cert_issuer_len": 18,
    "cert_subject_cn_mismatch": 1,
    "status_code": 200,
    "resp_time_ms": 1443,
    "redirect_count": 1,
    "final_url_mismatch": 1,
    "content_length": 1178,
    "mime_type": "text/html",
    "form_count": 0,
    "password_input_count": 0,
    "suspicious_js_calls": 0,
    "base64_count": 1,
    "external_link_count": 0,
    "external_resource_count": 1
  },
  {
    "url": "https://smartsquirrels.co/wpimages/null/votre/",
    "cert_valid_days": 90,
    "cert_days_to_expire": 72,
    "cert_issuer_len": 42,
    "cert_subject_cn_mismatch": 0,
    "status_code": 404,
    "resp_time_ms": 2055,
    "redirect_count": 0,
    "final_url_mismatch": 0,
    "content_length": 41573,
    "mime_type": "text/html",
    "form_count": 0,
    "password_input_count": 0,
    "suspicious_js_calls": 0,
    "base64_count": 0,
    "external_link_count": 2,
    "external_resource_count": 3
  },
  {
    "url": "https://agencyft.org/wpimages/null/votre/",
    "cert_valid_days": 90,
    "cert_days_to_expire": 49,
    "cert_issuer_len": 26,
    "cert_subject_cn_mismatch": 0,
    "status_code": 404,
    "resp_time_ms": 4693,
    "redirect_count": 0,
    "final_url_mismatch": 0,
    "content_length": 59005,
    "mime_type": "text/html",
    "form_count": 3,
    "password_input_count": 0,
    "suspicious_js_calls": 0,
    "base64_count": 0,
    "external_link_count": 3,
    "external_resource_count": 1
  },
  {
    "url": "https://sajfdgelmw3ps4aag3abidzdf2w3etc7y7mw376d3gsl4nrq6yyq.ar-io.dev/kBJRmItltvlwADbAFA8jLq2yTF_H2W3_w9mkvjYw9jE?",
    "cert_valid_days": 89,
    "cert_days_to_expire": 39,
    "cert_issuer_len": 18,
    "cert_subject_cn_mismatch": 1,
    "status_code": 404,
    "resp_time_ms": 1323,
    "redirect_count": 0,
    "final_url_mismatch": 0,
    "content_length": 9,
    "mime_type": "text/html",
    "form_count": 0,
    "password_input_count": 0,
    "suspicious_js_calls": 0,
    "base64_count": 0,
    "external_link_count": 0,
    "external_resource_count": 0
  },
  {
    "url": "https://new.express.adobe.com/webpage/5J0gIC7NVwLDp",
    "cert_valid_days": 394,
    "cert_days_to_expire": 338,
    "cert_issuer_len": 27,
    "cert_subject_cn_mismatch": 1,
    "status_code": 200,
    "resp_time_ms": 966,
    "redirect_count": 0,
    "final_url_mismatch": 0,
    "content_length": 72654,
    "mime_type": "text/html",
    "form_count": 0,
    "password_input_count": 0,
    "suspicious_js_calls": 0,
    "base64_count": 1,
    "external_link_count": 0,
    "external_resource_count": 0
  },
  {
    "url": "https://docs.google.com/presentation/d/e/2PACX-1vTIQknOb2GJ5V-MaHmv2GrJhHD5U0Ff645u6ec2q0F6_ekj5Pi4K1aqXONC9Zo0AroJJ7YbCUTBKeq3/pub?start=false&amp;loop=false&amp;delayms=3000",
    "cert_valid_days": 83,
    "cert_days_to_expire": 63,
    "cert_issuer_len": 26,
    "cert_subject_cn_mismatch": 1,
    "status_code": 410,
    "resp_time_ms": 762,
    "redirect_count": 0,
    "final_url_mismatch": 0,
    "content_length": 3286,
    "mime_type": "text/html",
    "form_count": 0,
    "password_input_count": 0,
    "suspicious_js_calls": 0,
    "base64_count": 0,
    "external_link_count": 0,
    "external_resource_count": 2
  },
  {
    "url": "https://auth-servicenewacse-admin.us-sea-1.linodeobjects.com/link.html",
    "cert_valid_days": 89,
    "cert_days_to_expire": 57,
    "cert_issuer_len": 18,
    "cert_subject_cn_mismatch": 1,
    "status_code": 404,
    "resp_time_ms": 614,
    "redirect_count": 0,
    "final_url_mismatch": 0,
    "content_length": 243,
    "mime_type": "application/xml",
    "form_count": 0,
    "password_input_count": 0,
    "suspicious_js_calls": 0,
    "base64_count": 0,
    "external_link_count": 0,
    "external_resource_count": 0
  },
  {
    "url": "https://inzaloits.co.za/fbb/fb/",
    "cert_valid_days": 89,
    "cert_days_to_expire": 70,
    "cert_issuer_len": 18,
    "cert_subject_cn_mismatch": 1,
    "status_code": 404,
    "resp_time_ms": 1941,
    "redirect_count": 0,
    "final_url_mismatch": 0,
    "content_length": 315,
    "mime_type": "text/html",
    "form_count": 0,
    "password_input_count": 0,
    "suspicious_js_calls": 0,
    "base64_count": 0,
    "external_link_count": 0,
    "external_resource_count": 0
  },
  {
    "url": "https://new.express.adobe.com/webpage/hsQUdCKY8iRW4/",
    "cert_valid_days": 394,
    "cert_days_to_expire": 338,
    "cert_issuer_len": 27,
    "cert_subject_cn_mismatch": 1,
    "status_code": 200,
    "resp_time_ms": 956,
    "redirect_count": 0,
    "final_url_mismatch": 0,
    "content_length": 72654,
    "mime_type": "text/html",
    "form_count": 0,
    "password_input_count": 0,
    "suspicious_js_calls": 0,
    "base64_count": 1,
    "external_link_count": 0,
    "external_resource_count": 0
  },
  {
    "url": "http://chengcoon.com/contracts/contract/",
    "cert_valid_days": 0,
    "cert_days_to_expire": 0,
    "cert_issuer_len": 0,
    "cert_subject_cn_mismatch": 1,
    "status_code": 404,
    "resp_time_ms": 354,
    "redirect_count": 0,
    "final_url_mismatch": 0,
    "content_length": 1023,
    "mime_type": "text/html",
    "form_count": 0,
    "password_input_count": 0,
    "suspicious_js_calls": 0,
    "base64_count": 0,
    "external_link_count": 0,
    "external_resource_count": 0
  },
  {
    "url": "https://new.express.adobe.com/webpage/jwvOBMEl4CxWV",
    "cert_valid_days": 394,
    "cert_days_to_expire": 338,
    "cert_issuer_len": 27,
    "cert_subject_cn_mismatch": 1,
    "status_code": 200,
    "resp_time_ms": 950,
    "redirect_count": 0,
    "final_url_mismatch": 0,
    "content_length": 72654,
    "mime_type": "text/html",
    "form_count": 0,
    "password_input_count": 0,
    "suspicious_js_calls": 0,
    "base64_count": 1,
    "external_link_count": 0,
    "external_resource_count": 0
  },
  {
    "url": "https://annual-wages-increase-revision-please-complete-document.us-east-1.linodeobjects.com/pending.html",
    "cert_valid_days": 89,
    "cert_days_to_expire": 59,
    "cert_issuer_len": 18,
    "cert_subject_cn_mismatch": 1,
    "status_code": 404,
    "resp_time_ms": 938,
    "redirect_count": 0,
    "final_url_mismatch": 0,
    "content_length": 275,
    "mime_type": "application/xml",
    "form_count": 0,
    "password_input_count": 0,
    "suspicious_js_calls": 0,
    "base64_count": 0,
    "external_link_count": 0,
    "external_resource_count": 0
  },
  {
    "url": "https://rvmidiapublicidade.rvmidiapublicidade.com",
    "cert_valid_days": 90,
    "cert_days_to_expire": 82,
    "cert_issuer_len": 26,
    "cert_subject_cn_mismatch": 1,
    "status_code": 403,
    "resp_time_ms": 536,
    "redirect_count": 0,
    "final_url_mismatch": 0,
    "content_length": 6744,
    "mime_type": "text/html",
    "form_count": 0,
    "password_input_count": 0,
    "suspicious_js_calls": 0,
    "base64_count": 1,
    "external_link_count": 0,
    "external_resource_count": 0
  },
  {
    "url": "https://toolsdistr.fr-par-1.linodeobjects.com/reference.html",
    "cert_valid_days": 89,
    "cert_days_to_expire": 54,
    "cert_issuer_len": 18,
    "cert_subject_cn_mismatch": 1,
    "status_code": 404,
    "resp_time_ms": 1138,
    "redirect_count": 0,
    "final_url_mismatch": 0,
    "content_length": 228,
    "mime_type": "application/xml",
    "form_count": 0,
    "password_input_count": 0,
    "suspicious_js_calls": 0,
    "base64_count": 0,
    "external_link_count": 0,
    "external_resource_count": 0
  },
  {
    "url": "https://jali.me/btvoiceintern",
    "cert_valid_days": 90,
    "cert_days_to_expire": 56,
    "cert_issuer_len": 26,
    "cert_subject_cn_mismatch": 0,
    "status_code": 403,
    "resp_time_ms": 801,
    "redirect_count": 0,
    "final_url_mismatch": 0,
    "content_length": 5448,
    "mime_type": "text/html",
    "form_count": 0,
    "password_input_count": 0,
    "suspicious_js_calls": 0,
    "base64_count": 0,
    "external_link_count": 1,
    "external_resource_count": 0
  },
  {
    "url": "https://new.express.adobe.com/webpage/M42tfcITrYxlv",
    "cert_valid_days": 394,
    "cert_days_to_expire": 338,
    "cert_issuer_len": 27,
    "cert_subject_cn_mismatch": 1,
    "status_code": 200,
    "resp_time_ms": 1262,
    "redirect_count": 0,
    "final_url_mismatch": 0,
    "content_length": 72654,
    "mime_type": "text/html",
    "form_count": 0,
    "password_input_count": 0,
    "suspicious_js_calls": 0,
    "base64_count": 1,
    "external_link_count": 0,
    "external_resource_count": 0
  },
  {
    "url": "https://rcl.ink/zFFJK",
    "cert_valid_days": 90,
    "cert_days_to_expire": 32,
    "cert_issuer_len": 26,
    "cert_subject_cn_mismatch": 0,
    "status_code": 200,
    "resp_time_ms": 870,
    "redirect_count": 0,
    "final_url_mismatch": 0,
    "content_length": 1029,
    "mime_type": "text/html",
    "form_count": 0,
    "password_input_count": 0,
    "suspicious_js_calls": 0,
    "base64_count": 0,
    "external_link_count": 0,
    "external_resource_count": 2
  },
  {
    "url": "https://rcl.ink/zqGvA",
    "cert_valid_days": 90,
    "cert_days_to_expire": 32,
    "cert_issuer_len": 26,
    "cert_subject_cn_mismatch": 0,
    "status_code": 200,
    "resp_time_ms": 901,
    "redirect_count": 0,
    "final_url_mismatch": 0,
    "content_length": 1029,
    "mime_type": "text/html",
    "form_count": 0,
    "password_input_count": 0,
    "suspicious_js_calls": 0,
    "base64_count": 0,
    "external_link_count": 0,
    "external_resource_count": 2
  },
  {
    "url": "https://thesouthbeachfoodtour.com/moussa8.html",
    "cert_valid_days": 89,
    "cert_days_to_expire": 32,
    "cert_issuer_len": 18,
    "cert_subject_cn_mismatch": 1,
    "status_code": 406,
    "resp_time_ms": 814,
    "redirect_count": 0,
    "final_url_mismatch": 0,
    "content_length": 226,
    "mime_type": "text/html",
    "form_count": 0,
    "password_input_count": 0,
    "suspicious_js_calls": 0,
    "base64_count": 0,
    "external_link_count": 0,
    "external_resource_count": 0
  },
  {
    "url": "http://100f4da.wcomhost.com/",
    "cert_valid_days": 0,
    "cert_days_to_expire": 0,
    "cert_issuer_len": 0,
    "cert_subject_cn_mismatch": 1,
    "status_code": 403,
    "resp_time_ms": 690,
    "redirect_count": 0,
    "final_url_mismatch": 0,
    "content_length": 300,
    "mime_type": "text/html",
    "form_count": 0,
    "password_input_count": 0,
    "suspicious_js_calls": 0,
    "base64_count": 0,
    "external_link_count": 0,
    "external_resource_count": 0
  },
  {
    "url": "https://docs.google.com/presentation/d/e/2PACX-1vTUdPIamkjDR_XvDTIdu9hl3dPEF1W0fdwAWCBx5ZPFkGsSlW-CMYZ0Q_lCHF9QHug8gLpJXiRGfrHI/pub?start=false&amp;loop=false&amp;delayms=3000&amp;slide=id.p",
    "cert_valid_days": 83,
    "cert_days_to_expire": 63,
    "cert_issuer_len": 26,
    "cert_subject_cn_mismatch": 1,
    "status_code": 403,
    "resp_time_ms": 747,
    "redirect_count": 0,
    "final_url_mismatch": 0,
    "content_length": 2994,
    "mime_type": "text/html",
    "form_count": 0,
    "password_input_count": 0,
    "suspicious_js_calls": 0,
    "base64_count": 0,
    "external_link_count": 0,
    "external_resource_count": 2
  },
  {
    "url": "https://docs.google.com/presentation/d/e/2PACX-1vSuxCuBzmnLQJsHTyFmOGWjhQr_oxIzs_e3q8U3jaVTfhG4STY7H9n2xAHg3HXiLoBfhX6xsprqQjgE/pub?start=false&amp;loop=false&amp;delayms=3000&amp;slide=id.p",
    "cert_valid_days": 83,
    "cert_days_to_expire": 63,
    "cert_issuer_len": 26,
    "cert_subject_cn_mismatch": 1,
    "status_code": 200,
    "resp_time_ms": 717,
    "redirect_count": 0,
    "final_url_mismatch": 0,
    "content_length": 86086,
    "mime_type": "text/html",
    "form_count": 0,
    "password_input_count": 0,
    "suspicious_js_calls": 0,
    "base64_count": 0,
    "external_link_count": 0,
    "external_resource_count": 3
  },
  {
    "url": "https://docs.google.com/presentation/d/e/2PACX-1vSuhLlGWDbldoZcVjN9UlKqxo1Bu8QVshfTcDNFdghotk6UOEbQWCkBPJ41YNK7XahyUPdkCNg9ntgb/pub?start=false&amp;loop=false&amp;delayms=3000&amp;slide=id.p",
    "cert_valid_days": 83,
    "cert_days_to_expire": 63,
    "cert_issuer_len": 26,
    "cert_subject_cn_mismatch": 1,
    "status_code": 200,
    "resp_time_ms": 6876,
    "redirect_count": 0,
    "final_url_mismatch": 0,
    "content_length": 78523,
    "mime_type": "text/html",
    "form_count": 0,
    "password_input_count": 0,
    "suspicious_js_calls": 0,
    "base64_count": 0,
    "external_link_count": 0,
    "external_resource_count": 3
  },
  {
    "url": "https://docs.google.com/presentation/d/e/2PACX-1vTecK6ezyhmu9TL3hJVEVurusaCkelMvO-nCFfvSJ1tmNs4GTDi1QhQOk-uepo7zKdrXCJOkBLN68fy/pub?start=false&amp;loop=false&amp;delayms=3000",
    "cert_valid_days": 83,
    "cert_days_to_expire": 63,
    "cert_issuer_len": 26,
    "cert_subject_cn_mismatch": 1,
    "status_code": 200,
    "resp_time_ms": 618,
    "redirect_count": 0,
    "final_url_mismatch": 0,
    "content_length": 81773,
    "mime_type": "text/html",
    "form_count": 0,
    "password_input_count": 0,
    "suspicious_js_calls": 0,
    "base64_count": 0,
    "external_link_count": 0,
    "external_resource_count": 3
  },
  {
    "url": "https://keepo.io/uipdatsd",
    "cert_valid_days": 393,
    "cert_days_to_expire": 186,
    "cert_issuer_len": 27,
    "cert_subject_cn_mismatch": 0,
    "status_code": 404,
    "resp_time_ms": 1818,
    "redirect_count": 0,
    "final_url_mismatch": 0,
    "content_length": 15084,
    "mime_type": "text/html",
    "form_count": 0,
    "password_input_count": 0,
    "suspicious_js_calls": 0,
    "base64_count": 0,
    "external_link_count": 0,
    "external_resource_count": 1
  },
  {
    "url": "https://new.express.adobe.com/webpage/OX6jxKrTd1P84",
    "cert_valid_days": 394,
    "cert_days_to_expire": 338,
    "cert_issuer_len": 27,
    "cert_subject_cn_mismatch": 1,
    "status_code": 200,
    "resp_time_ms": 1325,
    "redirect_count": 0,
    "final_url_mismatch": 0,
    "content_length": 72654,
    "mime_type": "text/html",
    "form_count": 0,
    "password_input_count": 0,
    "suspicious_js_calls": 0,
    "base64_count": 1,
    "external_link_count": 0,
    "external_resource_count": 0
  },
  {
    "url": "https://keepo.io/INUPDSETING",
    "cert_valid_days": 393,
    "cert_days_to_expire": 186,
    "cert_issuer_len": 27,
    "cert_subject_cn_mismatch": 0,
    "status_code": 404,
    "resp_time_ms": 1686,
    "redirect_count": 0,
    "final_url_mismatch": 0,
    "content_length": 15084,
    "mime_type": "text/html",
    "form_count": 0,
    "password_input_count": 0,
    "suspicious_js_calls": 0,
    "base64_count": 0,
    "external_link_count": 0,
    "external_resource_count": 1
  },
  {
    "url": "https://docs.google.com/presentation/d/e/2PACX-1vTIcUO2do_qqiriiDqhLjmpVWmFhWho_J4T2F89Kwp7AA_nw96MCuhpd0pFmkRoDHqt3Q7O0jQxOuog/pub?start=false&amp;loop=false&amp;delayms=3000",
    "cert_valid_days": 83,
    "cert_days_to_expire": 63,
    "cert_issuer_len": 26,
    "cert_subject_cn_mismatch": 1,
    "status_code": 200,
    "resp_time_ms": 1096,
    "redirect_count": 0,
    "final_url_mismatch": 0,
    "content_length": 79745,
    "mime_type": "text/html",
    "form_count": 0,
    "password_input_count": 0,
    "suspicious_js_calls": 0,
    "base64_count": 0,
    "external_link_count": 0,
    "external_resource_count": 3
  },
  {
    "url": "https://keepo.io/inupdseting/",
    "cert_valid_days": 393,
    "cert_days_to_expire": 186,
    "cert_issuer_len": 27,
    "cert_subject_cn_mismatch": 0,
    "status_code": 404,
    "resp_time_ms": 1695,
    "redirect_count": 0,
    "final_url_mismatch": 0,
    "content_length": 15084,
    "mime_type": "text/html",
    "form_count": 0,
    "password_input_count": 0,
    "suspicious_js_calls": 0,
    "base64_count": 0,
    "external_link_count": 0,
    "external_resource_count": 1
  },
  {
    "url": "https://keepo.io/uipdatsd/",
    "cert_valid_days": 393,
    "cert_days_to_expire": 186,
    "cert_issuer_len": 27,
    "cert_subject_cn_mismatch": 0,
    "status_code": 404,
    "resp_time_ms": 1628,
    "redirect_count": 0,
    "final_url_mismatch": 0,
    "content_length": 15084,
    "mime_type": "text/html",
    "form_count": 0,
    "password_input_count": 0,
    "suspicious_js_calls": 0,
    "base64_count": 0,
    "external_link_count": 0,
    "external_resource_count": 1
  },
  {
    "url": "https://new.express.adobe.com/webpage/mt1ADwJT9Lpg6",
    "cert_valid_days": 394,
    "cert_days_to_expire": 338,
    "cert_issuer_len": 27,
    "cert_subject_cn_mismatch": 1,
    "status_code": 200,
    "resp_time_ms": 1138,
    "redirect_count": 0,
    "final_url_mismatch": 0,
    "content_length": 72654,
    "mime_type": "text/html",
    "form_count": 0,
    "password_input_count": 0,
    "suspicious_js_calls": 0,
    "base64_count": 1,
    "external_link_count": 0,
    "external_resource_count": 0
  },
  {
    "url": "https://rest2.ubpages.com/citycurrent23/",
    "cert_valid_days": 89,
    "cert_days_to_expire": 79,
    "cert_issuer_len": 17,
    "cert_subject_cn_mismatch": 1,
    "status_code": 404,
    "resp_time_ms": 966,
    "redirect_count": 0,
    "final_url_mismatch": 0,
    "content_length": 47,
    "mime_type": "text/plain",
    "form_count": 0,
    "password_input_count": 0,
    "suspicious_js_calls": 0,
    "base64_count": 0,
    "external_link_count": 0,
    "external_resource_count": 0
  },
  {
    "url": "https://docs.google.com/presentation/d/e/2PACX-1vRcFzu5BTMZIkfNvBbtlSGcgtqNTVn0ih76dYhqOIOT31CKaD0vEcQzJ9iVUkY_PCJcXx2LSezfSwsc/pub?start=false&amp;loop=false&amp;delayms=3000",
    "cert_valid_days": 83,
    "cert_days_to_expire": 63,
    "cert_issuer_len": 26,
    "cert_subject_cn_mismatch": 1,
    "status_code": 200,
    "resp_time_ms": 677,
    "redirect_count": 0,
    "final_url_mismatch": 0,
    "content_length": 77457,
    "mime_type": "text/html",
    "form_count": 0,
    "password_input_count": 0,
    "suspicious_js_calls": 0,
    "base64_count": 0,
    "external_link_count": 0,
    "external_resource_count": 3
  },
  {
    "url": "https://acc0ch56xe.page.link/bjYi",
    "cert_valid_days": 83,
    "cert_days_to_expire": 63,
    "cert_issuer_len": 26,
    "cert_subject_cn_mismatch": 1,
    "status_code": 200,
    "resp_time_ms": 2770,
    "redirect_count": 1,
    "final_url_mismatch": 1,
    "content_length": 42659,
    "mime_type": "text/html",
    "form_count": 0,
    "password_input_count": 0,
    "suspicious_js_calls": 0,
    "base64_count": 0,
    "external_link_count": 2,
    "external_resource_count": 3
  },
  {
    "url": "https://new.express.adobe.com/webpage/9QAbLucTZNmwD",
    "cert_valid_days": 394,
    "cert_days_to_expire": 338,
    "cert_issuer_len": 27,
    "cert_subject_cn_mismatch": 1,
    "status_code": 200,
    "resp_time_ms": 1391,
    "redirect_count": 0,
    "final_url_mismatch": 0,
    "content_length": 72654,
    "mime_type": "text/html",
    "form_count": 0,
    "password_input_count": 0,
    "suspicious_js_calls": 0,
    "base64_count": 1,
    "external_link_count": 0,
    "external_resource_count": 0
  },
  {
    "url": "https://new.express.adobe.com/webpage/TZgHutUNRWC3x",
    "cert_valid_days": 394,
    "cert_days_to_expire": 338,
    "cert_issuer_len": 27,
    "cert_subject_cn_mismatch": 1,
    "status_code": 200,
    "resp_time_ms": 866,
    "redirect_count": 0,
    "final_url_mismatch": 0,
    "content_length": 72654,
    "mime_type": "text/html",
    "form_count": 0,
    "password_input_count": 0,
    "suspicious_js_calls": 0,
    "base64_count": 1,
    "external_link_count": 0,
    "external_resource_count": 0
  },
  {
    "url": "https://new.express.adobe.com/webpage/LnPdQCNJhMe8S",
    "cert_valid_days": 394,
    "cert_days_to_expire": 338,
    "cert_issuer_len": 27,
    "cert_subject_cn_mismatch": 1,
    "status_code": 200,
    "resp_time_ms": 1062,
    "redirect_count": 0,
    "final_url_mismatch": 0,
    "content_length": 72654,
    "mime_type": "text/html",
    "form_count": 0,
    "password_input_count": 0,
    "suspicious_js_calls": 0,
    "base64_count": 1,
    "external_link_count": 0,
    "external_resource_count": 0
  },
  {
    "url": "https://bn-028l.webcindario.com",
    "cert_valid_days": 89,
    "cert_days_to_expire": 13,
    "cert_issuer_len": 18,
    "cert_subject_cn_mismatch": 1,
    "status_code": 200,
    "resp_time_ms": 1588,
    "redirect_count": 0,
    "final_url_mismatch": 0,
    "content_length": 2624,
    "mime_type": "text/html",
    "form_count": 0,
    "password_input_count": 0,
    "suspicious_js_calls": 0,
    "base64_count": 0,
    "external_link_count": 1,
    "external_resource_count": 0
  },
  {
    "url": "https://docs.google.com/presentation/d/e/2PACX-1vQoBbribTJ7SX6QhQIpqbGT3gmVkN536gjFV5LgvF0Vo0GcT_LfrN_bHYnBUgtWonOwgohEOZEDrXZv/pub?start=false&amp;loop=false&amp;delayms=3000",
    "cert_valid_days": 83,
    "cert_days_to_expire": 63,
    "cert_issuer_len": 26,
    "cert_subject_cn_mismatch": 1,
    "status_code": 200,
    "resp_time_ms": 931,
    "redirect_count": 0,
    "final_url_mismatch": 0,
    "content_length": 80721,
    "mime_type": "text/html",
    "form_count": 0,
    "password_input_count": 0,
    "suspicious_js_calls": 0,
    "base64_count": 0,
    "external_link_count": 0,
    "external_resource_count": 3
  },
  {
    "url": "https://docs.google.com/presentation/d/e/2PACX-1vQhJ3kfJHlWSlKYo8H_8fRL_wnta-gAocIrrW3QNDAbZLwYrJPxQilBEKv_HIGmCuRP4Mmmg-1TV1n3/pub?start=false&amp;loop=false&amp;delayms=3000&amp;slide=id.p",
    "cert_valid_days": 83,
    "cert_days_to_expire": 63,
    "cert_issuer_len": 26,
    "cert_subject_cn_mismatch": 1,
    "status_code": 403,
    "resp_time_ms": 594,
    "redirect_count": 0,
    "final_url_mismatch": 0,
    "content_length": 2994,
    "mime_type": "text/html",
    "form_count": 0,
    "password_input_count": 0,
    "suspicious_js_calls": 0,
    "base64_count": 0,
    "external_link_count": 0,
    "external_resource_count": 2
  },
  {
    "url": "https://new.express.adobe.com/webpage/cmOYE5MoRavd0",
    "cert_valid_days": 394,
    "cert_days_to_expire": 338,
    "cert_issuer_len": 27,
    "cert_subject_cn_mismatch": 1,
    "status_code": 200,
    "resp_time_ms": 858,
    "redirect_count": 0,
    "final_url_mismatch": 0,
    "content_length": 72654,
    "mime_type": "text/html",
    "form_count": 0,
    "password_input_count": 0,
    "suspicious_js_calls": 0,
    "base64_count": 1,
    "external_link_count": 0,
    "external_resource_count": 0
  },
  {
    "url": "https://docs.google.com/presentation/d/e/2PACX-1vRe1wcXOwroGmq4W19lPC7GX4YDrKQYM_B5tbmMBRdG10rvSb2nN0VEK1tBoIEiN5yg0yzkWqBjLEaM/pub?start=false&amp;loop=false&amp;delayms=3000",
    "cert_valid_days": 83,
    "cert_days_to_expire": 63,
    "cert_issuer_len": 26,
    "cert_subject_cn_mismatch": 1,
    "status_code": 200,
    "resp_time_ms": 710,
    "redirect_count": 0,
    "final_url_mismatch": 0,
    "content_length": 78898,
    "mime_type": "text/html",
    "form_count": 0,
    "password_input_count": 0,
    "suspicious_js_calls": 0,
    "base64_count": 0,
    "external_link_count": 0,
    "external_resource_count": 3
  },
  {
    "url": "https://clickmotivefusion.com/dashboard",
    "cert_valid_days": 89,
    "cert_days_to_expire": 83,
    "cert_issuer_len": 17,
    "cert_subject_cn_mismatch": 0,
    "status_code": 200,
    "resp_time_ms": 755,
    "redirect_count": 0,
    "final_url_mismatch": 0,
    "content_length": 1078,
    "mime_type": "text/html",
    "form_count": 0,
    "password_input_count": 0,
    "suspicious_js_calls": 0,
    "base64_count": 1,
    "external_link_count": 0,
    "external_resource_count": 1
  },
  {
    "url": "https://ian-argentina.com.ar/wp-includes/Requests/Auth/secure/3/",
    "cert_valid_days": 89,
    "cert_days_to_expire": 79,
    "cert_issuer_len": 18,
    "cert_subject_cn_mismatch": 0,
    "status_code": 404,
    "resp_time_ms": 3038,
    "redirect_count": 0,
    "final_url_mismatch": 0,
    "content_length": 66202,
    "mime_type": "text/html",
    "form_count": 1,
    "password_input_count": 0,
    "suspicious_js_calls": 0,
    "base64_count": 0,
    "external_link_count": 1,
    "external_resource_count": 0
  },
  {
    "url": "https://654dsf1h65dfg1h65dgfh1.s3.us-east-005.backblazeb2.com/qer65g16erg.html#/esrhesrh.html/1O0f0c0nrc0tqhmu-17rzym621vl07y3a30/tla/2n9c2",
    "cert_valid_days": 89,
    "cert_days_to_expire": 69,
    "cert_issuer_len": 18,
    "cert_subject_cn_mismatch": 1,
    "status_code": 400,
    "resp_time_ms": 818,
    "redirect_count": 0,
    "final_url_mismatch": 0,
    "content_length": 167,
    "mime_type": "application/xml",
    "form_count": 0,
    "password_input_count": 0,
    "suspicious_js_calls": 0,
    "base64_count": 0,
    "external_link_count": 0,
    "external_resource_count": 0
  },
  {
    "url": "https://sites.google.com/view/webbdee2upgrding/home",
    "cert_valid_days": 83,
    "cert_days_to_expire": 63,
    "cert_issuer_len": 26,
    "cert_subject_cn_mismatch": 1,
    "status_code": 200,
    "resp_time_ms": 629,
    "redirect_count": 0,
    "final_url_mismatch": 0,
    "content_length": 59924,
    "mime_type": "text/html",
    "form_count": 0,
    "password_input_count": 0,
    "suspicious_js_calls": 0,
    "base64_count": 0,
    "external_link_count": 0,
    "external_resource_count": 3
  },
  {
    "url": "https://href.li/?https://glinzikkpo.online/CS2330/neww",
    "cert_valid_days": 89,
    "cert_days_to_expire": 69,
    "cert_issuer_len": 17,
    "cert_subject_cn_mismatch": 1,
    "status_code": 200,
    "resp_time_ms": 248,
    "redirect_count": 0,
    "final_url_mismatch": 0,
    "content_length": 490,
    "mime_type": "text/html",
    "form_count": 0,
    "password_input_count": 0,
    "suspicious_js_calls": 0,
    "base64_count": 0,
    "external_link_count": 1,
    "external_resource_count": 0
  },
  {
    "url": "https://www.lisoladelmovimento.it/it",
    "cert_valid_days": 0,
    "cert_days_to_expire": 0,
    "cert_issuer_len": 0,
    "cert_subject_cn_mismatch": 1,
    "status_code": 404,
    "resp_time_ms": 3660,
    "redirect_count": 0,
    "final_url_mismatch": 0,
    "content_length": 111193,
    "mime_type": "text/html",
    "form_count": 1,
    "password_input_count": 0,
    "suspicious_js_calls": 1,
    "base64_count": 0,
    "external_link_count": 4,
    "external_resource_count": 3
  },
  {
    "url": "http://www.lisoladelmovimento.it/it/",
    "cert_valid_days": 0,
    "cert_days_to_expire": 0,
    "cert_issuer_len": 0,
    "cert_subject_cn_mismatch": 1,
    "status_code": 404,
    "resp_time_ms": 2715,
    "redirect_count": 1,
    "final_url_mismatch": 0,
    "content_length": 111191,
    "mime_type": "text/html",
    "form_count": 1,
    "password_input_count": 0,
    "suspicious_js_calls": 1,
    "base64_count": 0,
    "external_link_count": 4,
    "external_resource_count": 3
  },
  {
    "url": "https://new.express.adobe.com/webpage/XrJgOmnLFtyMH",
    "cert_valid_days": 394,
    "cert_days_to_expire": 338,
    "cert_issuer_len": 27,
    "cert_subject_cn_mismatch": 1,
    "status_code": 200,
    "resp_time_ms": 971,
    "redirect_count": 0,
    "final_url_mismatch": 0,
    "content_length": 72654,
    "mime_type": "text/html",
    "form_count": 0,
    "password_input_count": 0,
    "suspicious_js_calls": 0,
    "base64_count": 1,
    "external_link_count": 0,
    "external_resource_count": 0
  }
]